[
  {
    "type": "function",
    "name": "activate",
    "inputs": [],
    "outputs": [],
    "stateMutability": "nonpayable"
  },
  {
    "type": "function",
    "name": "beat",
    "inputs": [],
    "outputs": [],
    "stateMutability": "nonpayable"
  },
  {
    "type": "function",
    "name": "currentReward",
    "inputs": [],
    "outputs": [
      {
        "name": "",
        "type": "uint256",
        "internalType": "uint256"
      }
    ],
    "stateMutability": "view"
  },
  {
    "type": "function",
    "name": "deactivate",
    "inputs": [],
    "outputs": [],
    "stateMutability": "nonpayable"
  },
  {
    "type": "function",
    "name": "frequency",
    "inputs": [],
    "outputs": [
      {
        "name": "",
        "type": "uint48",
        "internalType": "uint48"
      }
    ],
    "stateMutability": "view"
  },
  {
    "type": "function",
    "name": "resetBeat",
    "inputs": [],
    "outputs": [],
    "stateMutability": "nonpayable"
  },
  {
    "type": "function",
    "name": "setFrequency",
    "inputs": [
      {
        "name": "freq",
        "type": "uint48",
        "internalType": "uint48"
      }
    ],
    "outputs": [],
    "stateMutability": "nonpayable"
  },
  {
    "type": "function",
    "name": "setPSM",
    "inputs": [
      {
        "name": "psm",
        "type": "address",
        "internalType": "address"
      }
    ],
    "outputs": [],
    "stateMutability": "nonpayable"
  },
  {
    "type": "function",
    "name": "setRewardAuctionParams",
    "inputs": [
      {
        "name": "maxReward_",
        "type": "uint256",
        "internalType": "uint256"
      },
      {
        "name": "auctionDuration_",
        "type": "uint48",
        "internalType": "uint48"
      }
    ],
    "outputs": [],
    "stateMutability": "nonpayable"
  },
  {
    "type": "function",
    "name": "setVault",
    "inputs": [
      {
        "name": "vault",
        "type": "address",
        "internalType": "address"
      }
    ],
    "outputs": [],
    "stateMutability": "nonpayable"
  },
  {
    "type": "event",
    "name": "Activated",
    "inputs": [],
    "anonymous": false
  },
  {
    "type": "event",
    "name": "Beat",
    "inputs": [
      {
        "name": "timestamp_",
        "type": "uint256",
        "indexed": true,
        "internalType": "uint256"
      }
    ],
    "anonymous": false
  },
  {
    "type": "event",
    "name": "Deactivated",
    "inputs": [],
    "anonymous": false
  },
  {
    "type": "event",
    "name": "FrequencySet",
    "inputs": [
      {
        "name": "frequency",
        "type": "uint48",
        "indexed": true,
        "internalType": "uint48"
      }
    ],
    "anonymous": false
  },
  {
    "type": "event",
    "name": "PSMSet",
    "inputs": [
      {
        "name": "psm",
        "type": "address",
        "indexed": true,
        "internalType": "address"
      }
    ],
    "anonymous": false
  },
  {
    "type": "event",
    "name": "RewardIssued",
    "inputs": [
      {
        "name": "to_",
        "type": "address",
        "indexed": true,
        "internalType": "address"
      },
      {
        "name": "rewardAmount_",
        "type": "uint256",
        "indexed": true,
        "internalType": "uint256"
      }
    ],
    "anonymous": false
  },
  {
    "type": "event",
    "name": "RewardUpdated",
    "inputs": [
      {
        "name": "maxRewardAmount_",
        "type": "uint256",
        "indexed": true,
        "internalType": "uint256"
      },
      {
        "name": "auctionDuration_",
        "type": "uint48",
        "indexed": true,
        "internalType": "uint48"
      }
    ],
    "anonymous": false
  },
  {
    "type": "event",
    "name": "VaultSet",
    "inputs": [
      {
        "name": "vault",
        "type": "address",
        "indexed": true,
        "internalType": "address"
      }
    ],
    "anonymous": false
  },
  {
    "type": "error",
    "name": "Heart_Active",
    "inputs": []
  },
  {
    "type": "error",
    "name": "Heart_BeatAvailable",
    "inputs": []
  },
  {
    "type": "error",
    "name": "Heart_BeatStopped",
    "inputs": []
  },
  {
    "type": "error",
    "name": "Heart_InvalidParams",
    "inputs": []
  },
  {
    "type": "error",
    "name": "Heart_OutOfCycle",
    "inputs": []
  }
]
