[
  {
    "type": "function",
    "name": "governor",
    "inputs": [],
    "outputs": [
      {
        "name": "",
        "type": "address",
        "internalType": "address"
      }
    ],
    "stateMutability": "view"
  },
  {
    "type": "function",
    "name": "guardian",
    "inputs": [],
    "outputs": [
      {
        "name": "",
        "type": "address",
        "internalType": "address"
      }
    ],
    "stateMutability": "view"
  },
  {
    "type": "function",
    "name": "policy",
    "inputs": [],
    "outputs": [
      {
        "name": "",
        "type": "address",
        "internalType": "address"
      }
    ],
    "stateMutability": "view"
  },
  {
    "type": "function",
    "name": "vault",
    "inputs": [],
    "outputs": [
      {
        "name": "",
        "type": "address",
        "internalType": "address"
      }
    ],
    "stateMutability": "view"
  },
  {
    "type": "event",
    "name": "GovernorPulled",
    "inputs": [
      {
        "name": "from",
        "type": "address",
        "indexed": true,
        "internalType": "address"
      },
      {
        "name": "to",
        "type": "address",
        "indexed": true,
        "internalType": "address"
      }
    ],
    "anonymous": false
  },
  {
    "type": "event",
    "name": "GovernorPushed",
    "inputs": [
      {
        "name": "from",
        "type": "address",
        "indexed": true,
        "internalType": "address"
      },
      {
        "name": "to",
        "type": "address",
        "indexed": true,
        "internalType": "address"
      },
      {
        "name": "_effectiveImmediately",
        "type": "bool",
        "indexed": false,
        "internalType": "bool"
      }
    ],
    "anonymous": false
  },
  {
    "type": "event",
    "name": "GuardianPulled",
    "inputs": [
      {
        "name": "from",
        "type": "address",
        "indexed": true,
        "internalType": "address"
      },
      {
        "name": "to",
        "type": "address",
        "indexed": true,
        "internalType": "address"
      }
    ],
    "anonymous": false
  },
  {
    "type": "event",
    "name": "GuardianPushed",
    "inputs": [
      {
        "name": "from",
        "type": "address",
        "indexed": true,
        "internalType": "address"
      },
      {
        "name": "to",
        "type": "address",
        "indexed": true,
        "internalType": "address"
      },
      {
        "name": "_effectiveImmediately",
        "type": "bool",
        "indexed": false,
        "internalType": "bool"
      }
    ],
    "anonymous": false
  },
  {
    "type": "event",
    "name": "PolicyPulled",
    "inputs": [
      {
        "name": "from",
        "type": "address",
        "indexed": true,
        "internalType": "address"
      },
      {
        "name": "to",
        "type": "address",
        "indexed": true,
        "internalType": "address"
      }
    ],
    "anonymous": false
  },
  {
    "type": "event",
    "name": "PolicyPushed",
    "inputs": [
      {
        "name": "from",
        "type": "address",
        "indexed": true,
        "internalType": "address"
      },
      {
        "name": "to",
        "type": "address",
        "indexed": true,
        "internalType": "address"
      },
      {
        "name": "_effectiveImmediately",
        "type": "bool",
        "indexed": false,
        "internalType": "bool"
      }
    ],
    "anonymous": false
  },
  {
    "type": "event",
    "name": "VaultPulled",
    "inputs": [
      {
        "name": "from",
        "type": "address",
        "indexed": true,
        "internalType": "address"
      },
      {
        "name": "to",
        "type": "address",
        "indexed": true,
        "internalType": "address"
      }
    ],
    "anonymous": false
  },
  {
    "type": "event",
    "name": "VaultPushed",
    "inputs": [
      {
        "name": "from",
        "type": "address",
        "indexed": true,
        "internalType": "address"
      },
      {
        "name": "to",
        "type": "address",
        "indexed": true,
        "internalType": "address"
      },
      {
        "name": "_effectiveImmediately",
        "type": "bool",
        "indexed": false,
        "internalType": "bool"
      }
    ],
    "anonymous": false
  }
]
